kavian/__init__.py
kavian/eda/_colors.py
kavian/eda/config.py
kavian/eda/plot.py
kavian/eda/tabular.py
kavian/tables/__init__.py
kavian/tables/base.py
kavian/tables/config.py
kavian/tables/linear_model.py
kavian/tables/summary.py
kavian/tables/utils.py
kavian/tables/model_stats/__init__.py
kavian/tables/model_stats/model_results.py
kavian/tests/test_summaries/conftest.py
kavian/tests/test_summaries/test_base.py
kavian/tests/test_summaries/test_model_stats.py
kavian-0.3.0.dist-info/LICENSE
kavian-0.3.0.dist-info/METADATA
kavian-0.3.0.dist-info/WHEEL
kavian-0.3.0.dist-info/top_level.txt
kavian-0.3.0.dist-info/RECORD
