Metadata-Version: 2.1
Name: kavian
Version: 0.3.0
Summary: Python statistical modeling toolkit with built-in Pandas and Scikit-Learn integration
Author-email: Adam Torres Encarnacion <art5809@psu.edu>
License: MIT
Project-URL: repository, https://github.com/AdamPSU/Kavian
Classifier: Programming Language :: Python :: 3
Classifier: License :: OSI Approved :: MIT License
Classifier: Operating System :: OS Independent
Requires-Python: >=3.9
License-File: LICENSE
Requires-Dist: numpy
Requires-Dist: pandas
Requires-Dist: scikit-learn
Requires-Dist: rich
Requires-Dist: pytest
Requires-Dist: statsmodels
Requires-Dist: scipy
